LICENSE
MANIFEST.in
README.md
setup.cfg
setup.py
hautomation_x10/__init__.py
hautomation_x10/cmds.py
hautomation_x10/deploy.py
hautomation_x10/driver.py
hautomation_x10/settings.py
hautomation_x10/tests.py
hautomation_x10/utils.py
hautomation_x10.egg-info/PKG-INFO
hautomation_x10.egg-info/SOURCES.txt
hautomation_x10.egg-info/dependency_links.txt
hautomation_x10.egg-info/entry_points.txt
hautomation_x10.egg-info/top_level.txt
hautomation_x10/docs/plugin.txt